mewni/__init__.py
mewni/cli/__init__.py
mewni/cli/cli.py
mewni/cli/generate.py
mewni/cli/init.py
mewni/cli/migrate.py
mewni/core/__init__.py
mewni/core/app.py
mewni/core/ask_data_middleware.py
mewni/core/autoloader.py
mewni/core/bot.py
mewni/core/config.py
mewni/core/controller.py
mewni/core/controllers.py
mewni/core/ctx.py
mewni/core/db.py
mewni/core/filter_.py
mewni/core/functions.py
mewni/core/loader.py
mewni/core/mewni_object.py
mewni/core/middleware.py
mewni/core/model.py
mewni/core/register.py
mewni/core/scheduling.py
mewni/core/store.py
mewni/core/templates/__init__.py
mewni/templates/model.txt
mewni/templates/project/.env
mewni/templates/project/.gitignore
mewni/templates/project/README.md
mewni/templates/project/bot/__init__.py
mewni/templates/project/bot/config/__init__.py
mewni/templates/project/bot/config/app.py
mewni/templates/project/bot/config/env.py
mewni/templates/project/bot/controllers/__init__.py
mewni/templates/project/bot/controllers/start.py
mewni/templates/project/bot/filters/__init__.py
mewni/templates/project/bot/locales/ru.json
mewni/templates/project/bot/middlewares/__init__.py
mewni/templates/project/bot/models/__init__.py
mewni/templates/project/bot/services/__init__.py
mewni/templates/project/bot/stores/User.py
mewni/templates/project/bot/stores/__init__.py
mewni/templates/project/bot/templates/__init__.py
mewni/templates/project/bot/templates/example.xml
mewni/templates/project/bot/templates/message.xml
mewni/templates/project/bot/types/__init__.py
mewni/templates/project/bot/utils/__init__.py
mewni/templates/project/main.py
mewni/templates/project/pyproject.toml
mewni/tests/__init__.py
mewni/tests/check_tree_identic.py
mewni/tests/workspace.py
mewni/types/__init__.py
mewni/types/config.py
mewni/utils/__init__.py
mewni/utils/fmt.py
mewni/utils/get_class_fields.py
mewni/utils/is_async.py
mewni/utils/make_async.py
mewni/utils/prefix.py
mewni/utils/singleton.py
mewni-0.2.dist-info/entry_points.txt
mewni-0.2.dist-info/WHEEL
mewni-0.2.dist-info/METADATA
mewni-0.2.dist-info/RECORD
