Metadata-Version: 2.1
Name: mewni
Version: 0.2
Summary: Telegram bot framework
Home-page: https://github.com/sejjax/mewni
Keywords: telegram,bot,framework,aiogram,mtproto
Author: Danil Sokolov
Author-email: danilzyx@gmail.com
Requires-Python: >=3.10
Classifier: Development Status :: 2 - Pre-Alpha
Classifier: Environment :: Console
Classifier: Operating System :: MacOS :: MacOS X
Classifier: Operating System :: Microsoft :: Windows
Classifier: Operating System :: POSIX :: Linux
Classifier: Programming Language :: Python :: 3
Classifier: Programming Language :: Python :: 3.10
Classifier: Topic :: Internet
Classifier: Topic :: Software Development
Classifier: Topic :: Software Development :: Code Generators
Classifier: Topic :: Software Development :: Libraries :: Application Frameworks
Requires-Dist: Jinja2 (>=3.1.2,<4.0.0)
Requires-Dist: Werkzeug (>=2.1.2,<3.0.0)
Requires-Dist: aiogram (>=2.2.0)
Requires-Dist: aioredis (>=2.0.1)
Requires-Dist: aioschedule (>=0.5.2,<0.6.0)
Requires-Dist: click (>=8.1.3,<9.0.0)
Requires-Dist: cogapp (>=3.3.0,<4.0.0)
Requires-Dist: environs (>=9.5.0)
Requires-Dist: peewee (>=3.14.10)
Project-URL: Bug Tracker, https://github.com/sejjax/mewni/issues
Project-URL: Repository, https://github.com/sejjax/mewni
